MANIFEST.in
README
setup.py
appy.egg-info/PKG-INFO
appy.egg-info/SOURCES.txt
appy.egg-info/dependency_links.txt
appy.egg-info/requires.txt
appy.egg-info/top_level.txt
py2/appy/LICENSE
py2/appy/__init__.py
py2/appy/version.py
py2/appy/bin/__init__.py
py2/appy/bin/asksap.py
py2/appy/bin/backup.py
py2/appy/bin/checkldap.py
py2/appy/bin/checklo.py
py2/appy/bin/clean.py
py2/appy/bin/createdebrepo.py
py2/appy/bin/eggify.py
py2/appy/bin/generate.py
py2/appy/bin/job.py
py2/appy/bin/new.py
py2/appy/bin/odfclean.py
py2/appy/bin/odfgrep.py
py2/appy/bin/odfsub.py
py2/appy/bin/odfwalk.py
py2/appy/bin/restore.py
py2/appy/bin/startlo
py2/appy/bin/zip.py
py2/appy/bin/zopectl.py
py2/appy/fields/__init__.py
py2/appy/fields/action.py
py2/appy/fields/boolean.py
py2/appy/fields/calendar.py
py2/appy/fields/color.py
py2/appy/fields/computed.py
py2/appy/fields/custom.py
py2/appy/fields/date.py
py2/appy/fields/dict.py
py2/appy/fields/file.py
py2/appy/fields/float.py
py2/appy/fields/group.py
py2/appy/fields/hour.py
py2/appy/fields/info.py
py2/appy/fields/integer.py
py2/appy/fields/list.py
py2/appy/fields/multilingual.py
py2/appy/fields/page.py
py2/appy/fields/phase.py
py2/appy/fields/pod.py
py2/appy/fields/ref.py
py2/appy/fields/rich.py
py2/appy/fields/search.py
py2/appy/fields/select.py
py2/appy/fields/string.py
py2/appy/fields/switch.py
py2/appy/fields/text.py
py2/appy/fields/translations.py
py2/appy/fields/workflow.py
py2/appy/gen/__init__.py
py2/appy/gen/authenticate.py
py2/appy/gen/descriptors.py
py2/appy/gen/generator.py
py2/appy/gen/indexer.py
py2/appy/gen/installer.py
py2/appy/gen/layout.py
py2/appy/gen/mail.py
py2/appy/gen/migrator.py
py2/appy/gen/model.py
py2/appy/gen/monitoring.py
py2/appy/gen/navigate.py
py2/appy/gen/po.py
py2/appy/gen/utils.py
py2/appy/gen/validate.py
py2/appy/gen/mixins/TestMixin.py
py2/appy/gen/mixins/ToolMixin.py
py2/appy/gen/mixins/__init__.py
py2/appy/gen/templates/Class.pyt
py2/appy/gen/templates/Page.odt
py2/appy/gen/templates/__init__.pyt
py2/appy/gen/templates/config.pyt
py2/appy/gen/templates/testAll.pyt
py2/appy/gen/templates/wrappers.pyt
py2/appy/gen/tr/Appy.pot
py2/appy/gen/tr/ar.po
